pybench/__init__.py
pybench/__main__.py
pybench/bench_model.py
pybench/cli.py
pybench/compare.py
pybench/discovery.py
pybench/meta.py
pybench/overrides.py
pybench/params.py
pybench/profiles.py
pybench/run_model.py
pybench/run_store.py
pybench/runner.py
pybench/suite_sig.py
pybench/timing.py
pybench/utils.py
pybench/reporters/_ansi.py
pybench/reporters/charts.py
pybench/reporters/csv.py
pybench/reporters/diff.py
pybench/reporters/json.py
pybench/reporters/markdown.py
pybench/reporters/table.py
pybenchx-1.2.0.dist-info/licenses/LICENSE
pybenchx-1.2.0.dist-info/METADATA
pybenchx-1.2.0.dist-info/WHEEL
pybenchx-1.2.0.dist-info/entry_points.txt
pybenchx-1.2.0.dist-info/top_level.txt
pybenchx-1.2.0.dist-info/RECORD
