Metadata-Version: 2.4
Name: pybenchx
Version: 1.2.0
Summary: A tiny, precise microbenchmarking framework for Python
Author-email: fullzer4 <gabrielpelizzaro@gmail.com>
License: MIT
Project-URL: Homepage, https://github.com/fullzer4/pybenchx
Project-URL: Repository, https://github.com/fullzer4/pybenchx
Project-URL: Issues, https://github.com/fullzer4/pybenchx/issues
Keywords: benchmark,microbenchmark,performance,timeit
Classifier: Development Status :: 3 - Alpha
Classifier: Intended Audience :: Developers
Classifier: Topic :: Software Development :: Testing
Classifier: Environment :: Console
Classifier: License :: OSI Approved :: MIT License
Classifier: Programming Language :: Python
Classifier: Programming Language :: Python :: 3
Classifier: Programming Language :: Python :: 3 :: Only
Classifier: Programming Language :: Python :: 3.7
Classifier: Programming Language :: Python :: 3.8
Classifier: Programming Language :: Python :: 3.9
Classifier: Programming Language :: Python :: 3.10
Classifier: Programming Language :: Python :: 3.11
Classifier: Programming Language :: Python :: 3.12
Classifier: Programming Language :: Python :: 3.13
Classifier: Operating System :: OS Independent
Requires-Python: >=3.7
License-File: LICENSE
Dynamic: license-file
